{"anncomplete":false,"sources":[{"id":"18451177","name":"MEDLINE","url":"http://ncbi.nlm.nih.gov/pubmed/18451177"},{"name":"PMID","id":"18451177","url":"http://www.ncbi.nlm.nih.gov/pubmed/18451177"}],"entities":[{"classId":"e_1","part":"s1h1","offsets":[{"start":0,"text":"TRIM68"}],"confidence":{"state":"","who":["user:GNormPlus"],"prob":1},"fields":{},"normalizations":{}},{"classId":"e_2","part":"s1h1","offsets":[{"start":51,"text":"androgen receptor"}],"confidence":{"state":"","who":["user:GNormPlus"],"prob":1},"fields":{},"normalizations":{}},{"classId":"e_2","part":"s2p1","offsets":[{"start":4,"text":"androgen receptor"}],"confidence":{"state":"","who":["user:GNormPlus"],"prob":1},"fields":{},"normalizations":{}},{"classId":"e_1","part":"s2p1","offsets":[{"start":433,"text":"TRIM68"}],"confidence":{"state":"","who":["user:GNormPlus"],"prob":1},"fields":{},"normalizations":{}},{"classId":"e_1","part":"s2p1","offsets":[{"start":626,"text":"TRIM68"}],"confidence":{"state":"","who":["user:GNormPlus"],"prob":1},"fields":{},"normalizations":{}},{"classId":"e_1","part":"s2p1","offsets":[{"start":661,"text":"TIP60"}],"confidence":{"state":"","who":["user:GNormPlus"],"prob":1},"fields":{},"normalizations":{}},{"classId":"e_2","part":"s2p1","offsets":[{"start":671,"text":"p300"}],"confidence":{"state":"","who":["user:GNormPlus"],"prob":1},"fields":{},"normalizations":{}},{"classId":"e_1","part":"s2p1","offsets":[{"start":773,"text":"TRIM68"}],"confidence":{"state":"","who":["user:GNormPlus"],"prob":1},"fields":{},"normalizations":{}},{"classId":"e_1","part":"s2p1","offsets":[{"start":840,"text":"prostate-specific antigen"}],"confidence":{"state":"","who":["user:GNormPlus"],"prob":1},"fields":{},"normalizations":{}},{"classId":"e_1","part":"s2p1","offsets":[{"start":867,"text":"PSA"}],"confidence":{"state":"","who":["user:GNormPlus"],"prob":1},"fields":{},"normalizations":{}},{"classId":"e_1","part":"s2p1","offsets":[{"start":959,"text":"TRIM68"}],"confidence":{"state":"","who":["user:GNormPlus"],"prob":1},"fields":{},"normalizations":{}},{"classId":"e_1","part":"s2p1","offsets":[{"start":994,"text":"PSA"}],"confidence":{"state":"","who":["user:GNormPlus"],"prob":1},"fields":{},"normalizations":{}},{"classId":"e_1","part":"s2p1","offsets":[{"start":1077,"text":"TRIM68"}],"confidence":{"state":"","who":["user:GNormPlus"],"prob":1},"fields":{},"normalizations":{}},{"classId":"e_1","part":"s2p1","offsets":[{"start":1236,"text":"TRIM68"}],"confidence":{"state":"","who":["user:GNormPlus"],"prob":1},"fields":{},"normalizations":{}}],"relations":[{"classId":"r_4","type":"linked","directed":false,"entities":["s1h1|0,6","s1h1|51,68"],"confidence":{"state":"","who":["user:Ashish"],"prob":1}},{"classId":"r_4","type":"linked","directed":false,"entities":["s2p1|626,632","s2p1|671,675"],"confidence":{"state":"","who":["user:Ashish"],"prob":1}}],"metas":{},"annotatable":{"parts":["s1h1","s2h1","s2p1"]}}